indiquo/__init__.py
indiquo/cli/IndiQuoCLI.py
indiquo/cli/__init__.py
indiquo/core/BaseCandidatePredictor.py
indiquo/core/BaseScenePredictor.py
indiquo/core/Candidate.py
indiquo/core/CandidatePredictor.py
indiquo/core/CandidatePredictorDummy.py
indiquo/core/CandidatePredictorRW.py
indiquo/core/CandidatePredictorST.py
indiquo/core/CandidatePredictorSum.py
indiquo/core/CandidateWithScenes.py
indiquo/core/IndiQuo.py
indiquo/core/IndiQuoBase.py
indiquo/core/IndiQuoException.py
indiquo/core/IndiQuoSum.py
indiquo/core/ScenePrediction.py
indiquo/core/ScenePredictor.py
indiquo/core/ScenePredictorDummy.py
indiquo/core/__init__.py
indiquo/core/chunker/BaseChunker.py
indiquo/core/chunker/Chunk.py
indiquo/core/chunker/SentenceChunker.py
indiquo/core/chunker/__init__.py
indiquo/match/Match.py
indiquo/match/__init__.py
indiquo/training/__init__.py
indiquo/training/candidate/TrainCandidateClassifier.py
indiquo/training/candidate/TrainCandidateClassifierST.py
indiquo/training/candidate/__init__.py
indiquo/training/scene/TrainSceneIdentification.py
indiquo/training/scene/__init__.py
indiquo-0.1.0.dist-info/licenses/LICENSE
indiquo-0.1.0.dist-info/METADATA
indiquo-0.1.0.dist-info/WHEEL
indiquo-0.1.0.dist-info/entry_points.txt
indiquo-0.1.0.dist-info/top_level.txt
indiquo-0.1.0.dist-info/RECORD
