Metadata-Version: 2.4
Name: IndiQuo
Version: 0.1.0
Summary: IndiQuo is a tool for the detection of indirect quotations (summaries and paraphrases).
Author-email: Frederik Arnold <frederik.arnold@hu-berlin.de>
License:                                  Apache License
Project-URL: Homepage, https://hu.berlin/indiquo
Keywords: quotation detection,quotation identification,indirect citation extraction,natural language processing,nlp,text reuse
Classifier: Programming Language :: Python :: 3
Classifier: License :: OSI Approved :: Apache Software License
Classifier: Operating System :: OS Independent
Requires-Python: >=3.11
License-File: LICENSE
Requires-Dist: sentence-transformers>=3.4.1
Requires-Dist: dramatist>=0.0.7
Requires-Dist: kpcommons>=0.1.2
Requires-Dist: pysbd>=0.3.4
Requires-Dist: datasets>=3.4.1
Requires-Dist: evaluate>=0.4.3
Requires-Dist: accelerate>=1.5.2
Dynamic: license-file
